epsel.py
epsel-1.0.0.dist-info/LICENSE.txt
epsel-1.0.0.dist-info/METADATA
epsel-1.0.0.dist-info/WHEEL
epsel-1.0.0.dist-info/top_level.txt
epsel-1.0.0.dist-info/RECORD
