Metadata-Version: 2.1
Name: epsel
Version: 1.0.0
Summary: Ensure PySpark Executor Logging
Home-page: https://github.com/soxofaan/epsel
Author: Stefaan Lippens
License: UNKNOWN
Platform: UNKNOWN
Classifier: Programming Language :: Python :: 3
Classifier: License :: OSI Approved :: MIT License
Classifier: Operating System :: OS Independent
Requires-Python: >=3.5
Provides-Extra: dev
Requires-Dist: pytest ; extra == 'dev'
Requires-Dist: pyspark ; extra == 'dev'
